utrello/__init__.py
utrello/api.py
utrello/model.py
utrello-0.8.1.dist-info/entry_points.txt
utrello-0.8.1.dist-info/LICENSE
utrello-0.8.1.dist-info/WHEEL
utrello-0.8.1.dist-info/METADATA
utrello-0.8.1.dist-info/RECORD
