Metadata-Version: 2.1
Name: utrello
Version: 0.8.1
Summary: 
License: MIT
Author: Davi Koscianski Vidal
Author-email: davividal@gmail.com
Requires-Python: >=3.8,<4.0
Classifier: License :: OSI Approved :: MIT License
Classifier: Programming Language :: Python :: 3
Classifier: Programming Language :: Python :: 3.10
Classifier: Programming Language :: Python :: 3.8
Classifier: Programming Language :: Python :: 3.9
Requires-Dist: pandas (>=1.4.3,<2.0.0)
Requires-Dist: requests (>=2.28.0,<3.0.0)
